{
  "feature": "nomansland:crag_rock",
  "placement": [
    {
      "type": "nomansland:density_function_based_count",
      "noise_function": "nomansland:default",

      "noise_scale": 1.0,

      "noise_minimum": 0.1,                   
      "noise_maximum": 0.9,  

      "count_minimum": 0,          
      "count_maximum": 1
    },
    {
      "type": "minecraft:in_square"
    },
    {
      "type": "minecraft:heightmap",
      "heightmap": "OCEAN_FLOOR_WG"
    },
    {
      "type": "minecraft:biome"
    }
  ]
}
